windowsxpl/__init__.py
windowsxpl/projects/__init__.py
windowsxpl/projects/dimension_reduction.py
windowsxpl/projects/main_stand.py
windowsxpl/root/__init__.py
windowsxpl/root/model_automl_with_auto_dt.py
windowsxpl/src/__init__.py
windowsxpl/src/config.py
windowsxpl/src/evaluation.py
windowsxpl/src/feature_engineering.py
windowsxpl/src/feature_processor.py
windowsxpl/src/model_automl.py
windowsxpl/src/model_ensemble.py
windowsxpl/src/model_stacking.py
windowsxpl/src/model_tuning.py
windowsxpl/src/model_wq.py
windowsxpl-0.4.0.dist-info/METADATA
windowsxpl-0.4.0.dist-info/WHEEL
windowsxpl-0.4.0.dist-info/entry_points.txt
windowsxpl-0.4.0.dist-info/top_level.txt
windowsxpl-0.4.0.dist-info/RECORD
